cloudict/__init__.py
cloudict/webdict.py
cloudict-0.0.7.dist-info/METADATA
cloudict-0.0.7.dist-info/RECORD
cloudict-0.0.7.dist-info/WHEEL
cloudict-0.0.7.dist-info/top_level.txt
