Metadata-Version: 2.1
Name: cloudict
Version: 0.0.7
Summary: a dict backed by cloud
Home-page: https://github.com/yyu/cloudict
Author: Yuan "Forrest" Yu
Author-email: yy@yuyuan.org
License: UNKNOWN
Platform: UNKNOWN
Classifier: Programming Language :: Python :: 3
Classifier: License :: OSI Approved :: MIT License
Classifier: Operating System :: OS Independent
